cuqipy_pytorch/__init__.py
cuqipy_pytorch/_version.py
cuqipy_pytorch/distribution.py
cuqipy_pytorch/model.py
cuqipy_pytorch/sampler.py
cuqipy_pytorch-0.5.0.dist-info/licenses/LICENSE
cuqipy_pytorch-0.5.0.dist-info/METADATA
cuqipy_pytorch-0.5.0.dist-info/WHEEL
cuqipy_pytorch-0.5.0.dist-info/top_level.txt
cuqipy_pytorch-0.5.0.dist-info/RECORD
