Metadata-Version: 2.4
Name: CUQIpy-PyTorch
Version: 0.5.0
Summary: CUQIpy plugin for PyTorch
Maintainer-email: "Nicolai A. B. Riis" <nabr@dtu.dk>, "Jakob S. Jørgensen" <jakj@dtu.dk>, "Amal M. Alghamdi" <amaal@dtu.dk>, Chao Zhang <chaz@dtu.dk>
License:                                  Apache License
Project-URL: Source, https://github.com/CUQI-DTU/CUQIpy-PyTorch
Project-URL: Download, https://github.com/CUQI-DTU/CUQIpy-PyTorch/releases
Requires-Python: >=3.8
License-File: LICENSE
Requires-Dist: torch
Requires-Dist: pyro-ppl
Requires-Dist: cuqipy
Dynamic: license-file
